{"ast":null,"code":"function _extends() { _extends = Object.assign ? Object.assign.bind() : function (target) { for (var i = 1; i < arguments.length; i++) { var source = arguments[i]; for (var key in source) { if (Object.prototype.hasOwnProperty.call(source, key)) { target[key] = source[key]; } } } return target; }; return _extends.apply(this, arguments); }\n\nimport React from 'react';\nimport { AutoLinkHeader, Example, Link as PatternflyThemeLink } from 'theme-patternfly-org/components';\nimport '../../../../node_modules/@patternfly/react-core/src/components/Alert/examples/./alert.css';\nimport UsersIcon from '@patternfly/react-icons/dist/esm/icons/users-icon';\nimport BoxIcon from '@patternfly/react-icons/dist/esm/icons/box-icon';\nimport DatabaseIcon from '@patternfly/react-icons/dist/esm/icons/database-icon';\nimport ServerIcon from '@patternfly/react-icons/dist/esm/icons/server-icon';\nimport LaptopIcon from '@patternfly/react-icons/dist/esm/icons/laptop-icon';\nvar pageData = {\n  \"id\": \"Alert\",\n  \"section\": \"components\",\n  \"source\": \"react\",\n  \"slug\": \"/components/alert/react\",\n  \"sourceLink\": \"https://github.com/patternfly/patternfly-react/blob/main/packages/docs/packages/react-core/src/components/Alert/examples/Alert.md\",\n  \"propComponents\": [{\n    \"name\": \"Alert\",\n    \"description\": \"\",\n    \"props\": [{\n      \"name\": \"actionClose\",\n      \"type\": \"React.ReactNode\",\n      \"description\": \"Close button; use the alertActionCloseButton component\"\n    }, {\n      \"name\": \"actionLinks\",\n      \"type\": \"React.ReactNode\",\n      \"description\": \"Action links; use a single alertActionLink component or multiple wrapped in an array or React.Fragment\"\n    }, {\n      \"name\": \"aria-label\",\n      \"type\": \"string\",\n      \"description\": \"Adds accessible text to the alert\",\n      \"defaultValue\": \"`${capitalize(variant)} Alert`\"\n    }, {\n      \"name\": \"children\",\n      \"type\": \"React.ReactNode\",\n      \"description\": \"Content rendered inside the alert\",\n      \"defaultValue\": \"''\"\n    }, {\n      \"name\": \"className\",\n      \"type\": \"string\",\n      \"description\": \"Additional classes added to the alert\",\n      \"defaultValue\": \"''\"\n    }, {\n      \"name\": \"customIcon\",\n      \"type\": \"React.ReactNode\",\n      \"description\": \"Set a custom icon to the alert. If not set the icon is set according to the variant\"\n    }, {\n      \"name\": \"isExpandable\",\n      \"type\": \"boolean\",\n      \"description\": \"Flag indicating that the alert is expandable\",\n      \"defaultValue\": \"false\"\n    }, {\n      \"name\": \"isInline\",\n      \"type\": \"boolean\",\n      \"description\": \"Flag to indicate if the alert is inline\",\n      \"defaultValue\": \"false\"\n    }, {\n      \"name\": \"isLiveRegion\",\n      \"type\": \"boolean\",\n      \"description\": \"Flag to indicate if the alert is in a live region\",\n      \"defaultValue\": \"false\"\n    }, {\n      \"name\": \"isPlain\",\n      \"type\": \"boolean\",\n      \"description\": \"Flag to indicate if the alert is plain\",\n      \"defaultValue\": \"false\"\n    }, {\n      \"name\": \"onMouseEnter\",\n      \"type\": \"No type info\",\n      \"defaultValue\": \"() => {}\"\n    }, {\n      \"name\": \"onMouseLeave\",\n      \"type\": \"No type info\",\n      \"defaultValue\": \"() => {}\"\n    }, {\n      \"name\": \"onTimeout\",\n      \"type\": \"() => void\",\n      \"description\": \"Function to be executed on alert timeout. Relevant when the timeout prop is set\",\n      \"defaultValue\": \"() => {}\"\n    }, {\n      \"name\": \"ouiaSafe\",\n      \"type\": \"No type info\",\n      \"defaultValue\": \"true\"\n    }, {\n      \"name\": \"timeout\",\n      \"type\": \"number | boolean\",\n      \"description\": \"If set to true, the timeout is 8000 milliseconds. If a number is provided, alert will be dismissed after that amount of time in milliseconds.\",\n      \"defaultValue\": \"false\"\n    }, {\n      \"name\": \"timeoutAnimation\",\n      \"type\": \"number\",\n      \"description\": \"If the user hovers over the alert and `timeout` expires, this is how long to wait before finally dismissing the alert\",\n      \"defaultValue\": \"3000\"\n    }, {\n      \"name\": \"title\",\n      \"type\": \"React.ReactNode\",\n      \"description\": \"Title of the alert\",\n      \"required\": true\n    }, {\n      \"name\": \"titleHeadingLevel\",\n      \"type\": \"'h1' | 'h2' | 'h3' | 'h4' | 'h5' | 'h6'\",\n      \"description\": \"Sets the heading level to use for the alert title. Default is h4.\",\n      \"defaultValue\": \"'h4'\"\n    }, {\n      \"name\": \"toggleAriaLabel\",\n      \"type\": \"string\",\n      \"description\": \"Adds accessible text to the alert Toggle\",\n      \"defaultValue\": \"`${capitalize(variant)} alert details`\"\n    }, {\n      \"name\": \"tooltipPosition\",\n      \"type\": \"| TooltipPosition\\n| 'auto'\\n| 'top'\\n| 'bottom'\\n| 'left'\\n| 'right'\\n| 'top-start'\\n| 'top-end'\\n| 'bottom-start'\\n| 'bottom-end'\\n| 'left-start'\\n| 'left-end'\\n| 'right-start'\\n| 'right-end'\",\n      \"description\": \"Position of the tooltip which is displayed if text is truncated\"\n    }, {\n      \"name\": \"truncateTitle\",\n      \"type\": \"number\",\n      \"description\": \"Truncate title to number of lines\",\n      \"defaultValue\": \"0\"\n    }, {\n      \"name\": \"variant\",\n      \"type\": \"'success' | 'danger' | 'warning' | 'info' | 'default'\",\n      \"description\": \"Adds alert variant styles\",\n      \"defaultValue\": \"AlertVariant.default\"\n    }, {\n      \"name\": \"variantLabel\",\n      \"type\": \"string\",\n      \"description\": \"Variant label text for screen readers\",\n      \"defaultValue\": \"`${capitalize(variant)} alert:`\"\n    }]\n  }, {\n    \"name\": \"AlertActionCloseButton\",\n    \"description\": \"\",\n    \"props\": [{\n      \"name\": \"aria-label\",\n      \"type\": \"string\",\n      \"description\": \"Aria Label for the Close button\",\n      \"defaultValue\": \"''\"\n    }, {\n      \"name\": \"className\",\n      \"type\": \"string\",\n      \"description\": \"Additional classes added to the AlertActionCloseButton\",\n      \"defaultValue\": \"''\"\n    }, {\n      \"name\": \"onClose\",\n      \"type\": \"() => void\",\n      \"description\": \"A callback for when the close button is clicked\",\n      \"defaultValue\": \"() => undefined as any\"\n    }, {\n      \"name\": \"variantLabel\",\n      \"type\": \"string\",\n      \"description\": \"Variant Label for the Close button\"\n    }]\n  }, {\n    \"name\": \"AlertActionLink\",\n    \"description\": \"\",\n    \"props\": [{\n      \"name\": \"children\",\n      \"type\": \"string\",\n      \"description\": \"Content rendered inside the AlertLinkAction\"\n    }, {\n      \"name\": \"className\",\n      \"type\": \"string\",\n      \"description\": \"Additional classes added to the AlertActionLink\",\n      \"defaultValue\": \"''\"\n    }]\n  }],\n  \"cssPrefix\": [\"pf-c-alert\"],\n  \"examples\": [\"Types\", \"Variations\", \"Inline types\", \"Inline variations\", \"Inline plain types\", \"Inline plain variations\", \"Expandable\", \"Static live region alert\", \"Dynamic live region alert\", \"Async live region alert\", \"Alert timeout\", \"Truncate\", \"Custom icons\"]\n};\npageData.liveContext = {\n  UsersIcon: UsersIcon,\n  BoxIcon: BoxIcon,\n  DatabaseIcon: DatabaseIcon,\n  ServerIcon: ServerIcon,\n  LaptopIcon: LaptopIcon\n};\npageData.examples = {\n  'Types': function Types(props) {\n    return /*#__PURE__*/React.createElement(Example, _extends({}, pageData, props, {\n      \"code\": \"import React from 'react';\\nimport { Alert } from '@patternfly/react-core';\\n\\nconst Types = () => (\\n  <React.Fragment>\\n    <Alert title=\\\"Default alert title\\\" />\\n    <Alert variant=\\\"info\\\" title=\\\"Info alert title\\\" />\\n    <Alert variant=\\\"success\\\" title=\\\"Success alert title\\\" />\\n    <Alert variant=\\\"warning\\\" title=\\\"Warning alert title\\\" />\\n    <Alert variant=\\\"danger\\\" title=\\\"Danger alert title\\\" />\\n  </React.Fragment>\\n)\",\n      \"title\": \"Types\",\n      \"lang\": \"ts\"\n    }));\n  },\n  'Variations': function Variations(props) {\n    return /*#__PURE__*/React.createElement(Example, _extends({}, pageData, props, {\n      \"code\": \"import React from 'react';\\nimport { Alert, AlertActionCloseButton, AlertActionLink } from '@patternfly/react-core';\\n\\nconst Variations = () => (\\n  <React.Fragment>\\n    <Alert\\n      variant=\\\"success\\\"\\n      title=\\\"Success alert title\\\"\\n      actionClose={<AlertActionCloseButton onClose={() => alert('Clicked the close button')} />}\\n      actionLinks={\\n        <React.Fragment>\\n          <AlertActionLink onClick={() => alert('Clicked on View details')}>View details</AlertActionLink>\\n          <AlertActionLink onClick={() => alert('Clicked on Ignore')}>Ignore</AlertActionLink>\\n        </React.Fragment>\\n      }\\n    >\\n      <p>Success alert description. This should tell the user more information about the alert.</p>\\n    </Alert>\\n    <Alert variant=\\\"success\\\" title=\\\"Success alert title\\\" actionClose={<AlertActionCloseButton onClose={() => alert('Clicked the close button')} />}>\\n      <p>\\n        Success alert description. This should tell the user more information about the alert.{' '}\\n        <a href=\\\"#\\\">This is a link.</a>\\n      </p>\\n    </Alert>\\n    <Alert\\n      variant=\\\"success\\\"\\n      title=\\\"Success alert title\\\"\\n      actionClose={<AlertActionCloseButton onClose={() => alert('Clicked the close button')} />}\\n      actionLinks={\\n        <React.Fragment>\\n          <AlertActionLink onClick={() => alert('Clicked on View details')}>View details</AlertActionLink>\\n          <AlertActionLink onClick={() => alert('Clicked on Ignore')}>Ignore</AlertActionLink>\\n        </React.Fragment>\\n      }\\n    />\\n    <Alert variant=\\\"success\\\" title=\\\"Success alert title\\\" actionClose={<AlertActionCloseButton onClose={() => alert('Clicked the close button')} />} />\\n    <Alert variant=\\\"success\\\" title=\\\"h1 Success alert title\\\" titleHeadingLevel=\\\"h1\\\" />\\n    <Alert variant=\\\"success\\\" title=\\\"h6 Success alert title\\\" titleHeadingLevel=\\\"h6\\\" />\\n    </React.Fragment>\\n)\",\n      \"title\": \"Variations\",\n      \"lang\": \"ts\"\n    }));\n  },\n  'Inline types': function InlineTypes(props) {\n    return /*#__PURE__*/React.createElement(Example, _extends({}, pageData, props, {\n      \"code\": \"import React from 'react';\\nimport { Alert } from '@patternfly/react-core';\\n\\nconst InlineTypes = () => (\\n  <React.Fragment>\\n    <Alert variant=\\\"default\\\" isInline title=\\\"Default inline alert title\\\" />\\n    <Alert variant=\\\"info\\\" isInline title=\\\"Info inline alert title\\\" />\\n    <Alert variant=\\\"success\\\" isInline title=\\\"Success inline alert title\\\" />\\n    <Alert variant=\\\"warning\\\" isInline title=\\\"Warning inline alert title\\\" />\\n    <Alert variant=\\\"danger\\\" isInline title=\\\"Danger inline alert title\\\" />\\n  </React.Fragment>\\n)\",\n      \"title\": \"Inline types\",\n      \"lang\": \"ts\"\n    }));\n  },\n  'Inline variations': function InlineVariations(props) {\n    return /*#__PURE__*/React.createElement(Example, _extends({}, pageData, props, {\n      \"code\": \"import React from 'react';\\nimport { Alert, AlertActionCloseButton, AlertActionLink } from '@patternfly/react-core';\\n\\nconst InlineVariations = () => (\\n  <React.Fragment>\\n    <Alert\\n      isInline\\n      variant=\\\"success\\\"\\n      title=\\\"Success alert title\\\"\\n      actionClose={<AlertActionCloseButton onClose={() => alert('Clicked the close button')} />}\\n      actionLinks={\\n        <React.Fragment>\\n          <AlertActionLink onClick={() => alert('Clicked on View details')}>View details</AlertActionLink>\\n          <AlertActionLink onClick={() => alert('Clicked on Ignore')}>Ignore</AlertActionLink>\\n        </React.Fragment>\\n      }\\n    >\\n      <p>Success alert description. This should tell the user more information about the alert.</p>\\n    </Alert>\\n    <Alert isInline variant=\\\"success\\\" title=\\\"Success alert title\\\" actionClose={<AlertActionCloseButton onClose={() => alert('Clicked the close button')} />}>\\n      <p>\\n        Success alert description. This should tell the user more information about the alert.{' '}\\n        <a href=\\\"#\\\">This is a link.</a>\\n      </p>\\n    </Alert>\\n    <Alert\\n      isInline\\n      variant=\\\"success\\\"\\n      title=\\\"Success alert title\\\"\\n      actionClose={<AlertActionCloseButton onClose={() => alert('Clicked the close button')} />}\\n      actionLinks={\\n        <React.Fragment>\\n          <AlertActionLink onClick={() => alert('Clicked on View details')}>View details</AlertActionLink>\\n          <AlertActionLink onClick={() => alert('Clicked on Ignore')}>Ignore</AlertActionLink>\\n        </React.Fragment>\\n      }\\n    />\\n    <Alert\\n      isInline\\n      variant=\\\"success\\\"\\n      title=\\\"Success alert title\\\"\\n      actionClose={<AlertActionCloseButton onClose={() => alert('Clicked the close button')} />}\\n    />\\n    <Alert isInline variant=\\\"success\\\" title=\\\"Success alert title\\\" />\\n  </React.Fragment>\\n)\",\n      \"title\": \"Inline variations\",\n      \"lang\": \"ts\"\n    }));\n  },\n  'Inline plain types': function InlinePlainTypes(props) {\n    return /*#__PURE__*/React.createElement(Example, _extends({}, pageData, props, {\n      \"code\": \"import React from 'react';\\nimport { Alert } from '@patternfly/react-core';\\n\\nconst InlinePlainTypes = () => (\\n  <React.Fragment>\\n    <Alert variant=\\\"default\\\" isInline isPlain title=\\\"Default inline alert title\\\" />\\n    <Alert variant=\\\"info\\\" isInline isPlain title=\\\"Info inline alert title\\\" />\\n    <Alert variant=\\\"success\\\" isInline isPlain title=\\\"Success inline alert title\\\" />\\n    <Alert variant=\\\"warning\\\" isInline isPlain title=\\\"Warning inline alert title\\\" />\\n    <Alert variant=\\\"danger\\\" isInline isPlain title=\\\"Danger inline alert title\\\" />\\n  </React.Fragment>\\n)\",\n      \"title\": \"Inline plain types\",\n      \"lang\": \"ts\"\n    }));\n  },\n  'Inline plain variations': function InlinePlainVariations(props) {\n    return /*#__PURE__*/React.createElement(Example, _extends({}, pageData, props, {\n      \"code\": \"import React from 'react';\\nimport { Alert, AlertActionCloseButton, AlertActionLink } from '@patternfly/react-core';\\n\\nconst InlinePlainVariations = () => (\\n  <Alert\\n    isInline\\n    isPlain\\n    variant=\\\"success\\\"\\n    title=\\\"Success alert title\\\"\\n  >\\n    <p>Success alert description. This should tell the user more information about the alert.</p>\\n  </Alert>\\n)\",\n      \"title\": \"Inline plain variations\",\n      \"lang\": \"ts\"\n    }), /*#__PURE__*/React.createElement(\"p\", {\n      \"className\": \"ws-p\"\n    }, \"It is not recommended to use an inline plain alert with actionClose nor actionLinks.\"));\n  },\n  'Expandable': function Expandable(props) {\n    return /*#__PURE__*/React.createElement(Example, _extends({}, pageData, props, {\n      \"code\": \"import React from 'react';\\nimport { Alert, AlertActionCloseButton, AlertActionLink } from '@patternfly/react-core';\\n\\nconst Expandable = () => (\\n  <React.Fragment>\\n    <Alert\\n      isExpandable\\n      variant=\\\"success\\\"\\n      title=\\\"Success alert title\\\"\\n      actionClose={<AlertActionCloseButton onClose={() => alert('Clicked the close button')} />}\\n      actionLinks={\\n        <React.Fragment>\\n          <AlertActionLink onClick={() => alert('Clicked on View details')}>View details</AlertActionLink>\\n          <AlertActionLink onClick={() => alert('Clicked on Ignore')}>Ignore</AlertActionLink>\\n        </React.Fragment>\\n      }\\n    >\\n      <p>Success alert description. This should tell the user more information about the alert.</p>\\n    </Alert>\\n    <Alert\\n      isExpandable\\n      isInline\\n      variant=\\\"success\\\"\\n      title=\\\"Success alert title\\\"\\n      actionClose={<AlertActionCloseButton onClose={() => alert('Clicked the close button')} />}\\n      actionLinks={\\n        <React.Fragment>\\n          <AlertActionLink onClick={() => alert('Clicked on View details')}>View details</AlertActionLink>\\n          <AlertActionLink onClick={() => alert('Clicked on Ignore')}>Ignore</AlertActionLink>\\n        </React.Fragment>\\n      } \\n    >\\n      <p>Success alert description. This should tell the user more information about the alert.</p>\\n    </Alert>\\n  </React.Fragment>\\n)\",\n      \"title\": \"Expandable\",\n      \"lang\": \"ts\"\n    }), /*#__PURE__*/React.createElement(\"p\", {\n      \"className\": \"ws-p\"\n    }, \"It is not recommended to use an expandable alert within a toast Alert group. In such a case, the Alert could timeout before users would have time to interact and view the entire Alert.\"));\n  },\n  'Static live region alert': function StaticLiveRegionAlert(props) {\n    return /*#__PURE__*/React.createElement(Example, _extends({}, pageData, props, {\n      \"code\": \"import React from 'react';\\nimport { Alert, AlertActionCloseButton } from '@patternfly/react-core';\\n\\nconst StaticLiveRegionAlert = () => (\\n  <React.Fragment>\\n    <Alert\\n      isLiveRegion\\n      variant=\\\"info\\\"\\n      title=\\\"Default live region configuration\\\"\\n      actionClose={<AlertActionCloseButton onClose={() => alert('Clicked the close button')} />}\\n    >\\n      This alert uses the recommended <code>isLiveRegion</code> prop to automatically set ARIA attributes and CSS classes.\\n    </Alert>\\n    <Alert\\n      aria-live=\\\"assertive\\\"\\n      aria-relevant=\\\"additions text\\\"\\n      aria-atomic=\\\"true\\\"\\n      variant=\\\"info\\\"\\n      title=\\\"Customized live region\\\"\\n      actionClose={<AlertActionCloseButton onClose={() => alert('Clicked the close button')} />}\\n    >\\n      You can alternatively omit the <code>isLiveRegion</code> prop to specify ARIA attributes and CSS manually on\\n      the containing element.\\n    </Alert>\\n  </React.Fragment>\\n)\",\n      \"title\": \"Static live region alert\",\n      \"lang\": \"ts\"\n    }));\n  },\n  'Dynamic live region alert': function DynamicLiveRegionAlert(props) {\n    return /*#__PURE__*/React.createElement(Example, _extends({}, pageData, props, {\n      \"code\": \"import React from 'react';\\nimport { Alert, AlertGroup, AlertVariant, InputGroup } from '@patternfly/react-core';\\n\\ninterface AlertInfo {\\n  title: string;\\n  variant: AlertVariant;\\n  key: number;\\n}\\n\\nexport const DynamicLiveRegionAlert: React.FunctionComponent = () => {\\n  const [alerts, setAlerts] = React.useState<AlertInfo[]>([]);\\n  const getUniqueId: () => number = () => new Date().getTime();\\n  const btnClasses = ['pf-c-button', 'pf-m-secondary'].join(' ');\\n\\n  const addAlert = (alertInfo: AlertInfo) => {\\n    setAlerts(prevAlertInfo => [...prevAlertInfo, alertInfo]);\\n  };\\n\\n  const addSuccessAlert = () => {\\n    addAlert({\\n      title: 'Single success alert',\\n      variant: AlertVariant.success,\\n      key: getUniqueId()\\n    });\\n  };\\n  const addInfoAlert = () => {\\n    addAlert({\\n      title: 'Single info alert',\\n      variant: AlertVariant.info,\\n      key: getUniqueId()\\n    });\\n  };\\n  const addDangerAlert = () => {\\n    addAlert({\\n      title: 'Single danger alert',\\n      variant: AlertVariant.danger,\\n      key: getUniqueId()\\n    });\\n  };\\n\\n  return (\\n    <React.Fragment>\\n      <InputGroup style={{ marginBottom: '16px' }}>\\n        <button onClick={addSuccessAlert} type=\\\"button\\\" className={btnClasses}>\\n          Add single success alert\\n        </button>\\n        <button onClick={addInfoAlert} type=\\\"button\\\" className={btnClasses}>\\n          Add single info alert\\n        </button>\\n        <button onClick={addDangerAlert} type=\\\"button\\\" className={btnClasses}>\\n          Add single danger alert\\n        </button>\\n      </InputGroup>\\n      <AlertGroup isLiveRegion aria-live=\\\"polite\\\" aria-relevant=\\\"additions text\\\" aria-atomic=\\\"false\\\">\\n        {alerts.map(({ title, variant, key }) => (\\n          <Alert variant={variant} title={title} key={key} />\\n        ))}\\n      </AlertGroup>\\n    </React.Fragment>\\n  );\\n};\\n\",\n      \"title\": \"Dynamic live region alert\",\n      \"lang\": \"ts\"\n    }), /*#__PURE__*/React.createElement(\"p\", {\n      \"className\": \"ws-p\"\n    }, \"Alerts asynchronously appended into dynamic AlertGroups with isLiveRegion will be announced to assistive technology at the moment the change happens, following the strategy used for aria-atomic, which defaults to false. This means only changes of type \\\"addition\\\" will be announced.\"));\n  },\n  'Async live region alert': function AsyncLiveRegionAlert(props) {\n    return /*#__PURE__*/React.createElement(Example, _extends({}, pageData, props, {\n      \"code\": \"import React from 'react';\\nimport { Alert, AlertGroup, AlertVariant, ToggleGroup, ToggleGroupItem } from '@patternfly/react-core';\\n\\ninterface AlertInfo {\\n  title: string;\\n  variant: AlertVariant;\\n  key: number;\\n}\\n\\nexport const AsyncLiveRegionAlert: React.FunctionComponent = () => {\\n  const [alerts, setAlerts] = React.useState<AlertInfo[]>([]);\\n  const [isActive, setIsActive] = React.useState(false);\\n  const getUniqueId: () => number = () => new Date().getTime();\\n\\n  const addAlert = (alertInfo: AlertInfo) => {\\n    setAlerts(prevAlertInfo => [...prevAlertInfo, alertInfo]);\\n  };\\n\\n  React.useEffect(() => {\\n    let timer = null;\\n    if (isActive) {\\n      timer = setInterval(() => {\\n        addAlert({\\n          title: `Async alert number ${alerts.length + 1}`,\\n          variant: AlertVariant.info,\\n          key: getUniqueId()\\n        });\\n      }, 4500);\\n    } else {\\n      clearInterval(timer);\\n    }\\n\\n    return () => {\\n      clearInterval(timer);\\n    };\\n  }, [isActive, alerts]);\\n\\n  return (\\n    <React.Fragment>\\n      <ToggleGroup aria-label=\\\"Toggle asynchronous alerts\\\">\\n        <ToggleGroupItem\\n          text=\\\"Async alerts on\\\"\\n          buttonId=\\\"async-alerts-on\\\"\\n          isSelected={isActive}\\n          onChange={() => setIsActive(true)}\\n        />\\n        <ToggleGroupItem\\n          text=\\\"Async alerts off\\\"\\n          buttonId=\\\"async-alerts-off\\\"\\n          isSelected={!isActive}\\n          onChange={() => setIsActive(false)}\\n        />\\n      </ToggleGroup>\\n      <AlertGroup isLiveRegion>\\n        {alerts.map(({ title, variant, key }) => (\\n          <Alert variant={variant} title={title} key={key} />\\n        ))}\\n      </AlertGroup>\\n    </React.Fragment>\\n  );\\n};\\n\",\n      \"title\": \"Async live region alert\",\n      \"lang\": \"ts\"\n    }), /*#__PURE__*/React.createElement(\"p\", {\n      \"className\": \"ws-p\"\n    }, \"This shows how an alert could be triggered by an asynchronous event in the application. Note that you can customize how the alert will be announced to assistive technology. See the alert accessibility tab for more information.\"));\n  },\n  'Alert timeout': function AlertTimeout(props) {\n    return /*#__PURE__*/React.createElement(Example, _extends({}, pageData, props, {\n      \"code\": \"import React from 'react';\\nimport { Alert, AlertActionLink, AlertGroup, Button } from '@patternfly/react-core';\\n\\nconst AlertTimeout: React.FunctionComponent = () => {\\n  const [alerts, setAlerts] = React.useState<React.ReactNode[]>([]);\\n  const onClick = () => {\\n    const timeout = 8000;\\n    setAlerts(prevAlerts => {\\n      return [...prevAlerts,\\n        <Alert title=\\\"Default timeout Alert\\\" timeout={timeout} actionLinks={\\n          <React.Fragment>\\n            <AlertActionLink>View details</AlertActionLink>\\n            <AlertActionLink>Ignore</AlertActionLink>\\n          </React.Fragment>\\n        }>\\n          This alert will dismiss after {`${timeout / 1000} seconds`}\\n        </Alert>\\n      ]\\n    });\\n  }\\n\\n  return (\\n    <React.Fragment>\\n      <Button variant=\\\"secondary\\\" onClick={onClick}>Add alert</Button>\\n      <Button variant=\\\"secondary\\\" onClick={() => setAlerts([])}>Remove all alerts</Button>\\n      <AlertGroup isLiveRegion>\\n        {alerts}\\n      </AlertGroup>\\n    </React.Fragment>\\n  );\\n};\",\n      \"title\": \"Alert timeout\",\n      \"lang\": \"ts\"\n    }));\n  },\n  'Truncate': function Truncate(props) {\n    return /*#__PURE__*/React.createElement(Example, _extends({}, pageData, props, {\n      \"code\": \"import React from 'react';\\nimport { Alert } from '@patternfly/react-core';\\n\\nconst Truncate = () => (\\n  <React.Fragment>\\n    <Alert variant=\\\"info\\\" truncateTitle={1} title={`\\n    Lorem ipsum dolor sit amet, consectetur adipiscing elit. Curabitur pellentesque neque cursus enim fringilla tincidunt. Proin lobortis aliquam dictum. Nam vel ullamcorper nulla, nec blandit dolor. Vivamus pellentesque neque justo, nec accumsan nulla rhoncus id. Suspendisse mollis, tortor quis faucibus volutpat, sem leo fringilla turpis, ac lacinia augue metus in nulla. Cras vestibulum lacinia orci. Pellentesque sodales consequat interdum. Sed porttitor tincidunt metus nec iaculis. Pellentesque non commodo justo. Morbi feugiat rhoncus neque, vitae facilisis diam aliquam nec. Sed dapibus vitae quam at tristique. Nunc vel commodo mi. Mauris et rhoncus leo.\\n    `} />\\n    <Alert variant=\\\"warning\\\" truncateTitle={2} title={`\\n    Lorem ipsum dolor sit amet, consectetur adipiscing elit. Curabitur pellentesque neque cursus enim fringilla tincidunt. Proin lobortis aliquam dictum. Nam vel ullamcorper nulla, nec blandit dolor. Vivamus pellentesque neque justo, nec accumsan nulla rhoncus id. Suspendisse mollis, tortor quis faucibus volutpat, sem leo fringilla turpis, ac lacinia augue metus in nulla. Cras vestibulum lacinia orci. Pellentesque sodales consequat interdum. Sed porttitor tincidunt metus nec iaculis. Pellentesque non commodo justo. Morbi feugiat rhoncus neque, vitae facilisis diam aliquam nec. Sed dapibus vitae quam at tristique. Nunc vel commodo mi. Mauris et rhoncus leo.\\n    `} />\\n    <Alert variant=\\\"danger\\\" truncateTitle={3} title={`\\n    Lorem ipsum dolor sit amet, consectetur adipiscing elit. Curabitur pellentesque neque cursus enim fringilla tincidunt. Proin lobortis aliquam dictum. Nam vel ullamcorper nulla, nec blandit dolor. Vivamus pellentesque neque justo, nec accumsan nulla rhoncus id. Suspendisse mollis, tortor quis faucibus volutpat, sem leo fringilla turpis, ac lacinia augue metus in nulla. Cras vestibulum lacinia orci. Pellentesque sodales consequat interdum. Sed porttitor tincidunt metus nec iaculis. Pellentesque non commodo justo. Morbi feugiat rhoncus neque, vitae facilisis diam aliquam nec. Sed dapibus vitae quam at tristique. Nunc vel commodo mi. Mauris et rhoncus leo.\\n    `} />\\n  </React.Fragment>\\n)\",\n      \"title\": \"Truncate\",\n      \"lang\": \"ts\"\n    }));\n  },\n  'Custom icons': function CustomIcons(props) {\n    return /*#__PURE__*/React.createElement(Example, _extends({}, pageData, props, {\n      \"code\": \"import React from 'react';\\nimport { Alert } from '@patternfly/react-core';\\nimport UsersIcon from '@patternfly/react-icons/dist/esm/icons/users-icon';\\nimport BoxIcon from '@patternfly/react-icons/dist/esm/icons/box-icon';\\nimport DatabaseIcon from '@patternfly/react-icons/dist/esm/icons/database-icon';\\nimport ServerIcon from '@patternfly/react-icons/dist/esm/icons/server-icon';\\nimport LaptopIcon from '@patternfly/react-icons/dist/esm/icons/laptop-icon';\\n\\nconst CustomIcons = () => (\\n  <React.Fragment>\\n    <Alert customIcon={<UsersIcon />} title=\\\"Default alert title\\\" />\\n    <Alert customIcon={<BoxIcon />} variant=\\\"info\\\" title=\\\"Info alert title\\\" />\\n    <Alert customIcon={<DatabaseIcon />} variant=\\\"success\\\" title=\\\"Success alert title\\\" />\\n    <Alert customIcon={<ServerIcon />} variant=\\\"warning\\\" title=\\\"Warning alert title\\\" />\\n    <Alert customIcon={<LaptopIcon />} variant=\\\"danger\\\" title=\\\"Danger alert title\\\" />\\n  </React.Fragment>\\n)\",\n      \"title\": \"Custom icons\",\n      \"lang\": \"ts\"\n    }));\n  }\n};\n\nvar Component = function Component() {\n  return /*#__PURE__*/React.createElement(React.Fragment, null, /*#__PURE__*/React.createElement(AutoLinkHeader, {\n    \"id\": \"examples\",\n    \"size\": \"h2\",\n    \"className\": \"ws-title ws-h2\"\n  }, \"Examples\"), React.createElement(pageData.examples[\"Types\"]), React.createElement(pageData.examples[\"Variations\"]), React.createElement(pageData.examples[\"Inline types\"]), React.createElement(pageData.examples[\"Inline variations\"]), React.createElement(pageData.examples[\"Inline plain types\"]), React.createElement(pageData.examples[\"Inline plain variations\"]), React.createElement(pageData.examples[\"Expandable\"]), React.createElement(pageData.examples[\"Static live region alert\"]), React.createElement(pageData.examples[\"Dynamic live region alert\"]), React.createElement(pageData.examples[\"Async live region alert\"]), React.createElement(pageData.examples[\"Alert timeout\"]), React.createElement(pageData.examples[\"Truncate\"]), React.createElement(pageData.examples[\"Custom icons\"]));\n};\n\nComponent.displayName = 'ComponentsAlertReactDocs';\nComponent.pageData = pageData;\nexport default Component;","map":{"version":3,"names":["React","AutoLinkHeader","Example","Link","PatternflyThemeLink","UsersIcon","BoxIcon","DatabaseIcon","ServerIcon","LaptopIcon","pageData","liveContext","examples","props","Component","createElement","displayName"],"sources":["/Users/jschuler/Code/patternfly-quickstarts/packages/docs/src/generated/components/alert/react.js"],"sourcesContent":["import React from 'react';\nimport { AutoLinkHeader, Example, Link as PatternflyThemeLink } from 'theme-patternfly-org/components';\nimport '../../../../node_modules/@patternfly/react-core/src/components/Alert/examples/./alert.css';\nimport UsersIcon from '@patternfly/react-icons/dist/esm/icons/users-icon';\nimport BoxIcon from '@patternfly/react-icons/dist/esm/icons/box-icon';\nimport DatabaseIcon from '@patternfly/react-icons/dist/esm/icons/database-icon';\nimport ServerIcon from '@patternfly/react-icons/dist/esm/icons/server-icon';\nimport LaptopIcon from '@patternfly/react-icons/dist/esm/icons/laptop-icon';\nconst pageData = {\n  \"id\": \"Alert\",\n  \"section\": \"components\",\n  \"source\": \"react\",\n  \"slug\": \"/components/alert/react\",\n  \"sourceLink\": \"https://github.com/patternfly/patternfly-react/blob/main/packages/docs/packages/react-core/src/components/Alert/examples/Alert.md\",\n  \"propComponents\": [\n    {\n      \"name\": \"Alert\",\n      \"description\": \"\",\n      \"props\": [\n        {\n          \"name\": \"actionClose\",\n          \"type\": \"React.ReactNode\",\n          \"description\": \"Close button; use the alertActionCloseButton component\"\n        },\n        {\n          \"name\": \"actionLinks\",\n          \"type\": \"React.ReactNode\",\n          \"description\": \"Action links; use a single alertActionLink component or multiple wrapped in an array or React.Fragment\"\n        },\n        {\n          \"name\": \"aria-label\",\n          \"type\": \"string\",\n          \"description\": \"Adds accessible text to the alert\",\n          \"defaultValue\": \"`${capitalize(variant)} Alert`\"\n        },\n        {\n          \"name\": \"children\",\n          \"type\": \"React.ReactNode\",\n          \"description\": \"Content rendered inside the alert\",\n          \"defaultValue\": \"''\"\n        },\n        {\n          \"name\": \"className\",\n          \"type\": \"string\",\n          \"description\": \"Additional classes added to the alert\",\n          \"defaultValue\": \"''\"\n        },\n        {\n          \"name\": \"customIcon\",\n          \"type\": \"React.ReactNode\",\n          \"description\": \"Set a custom icon to the alert. If not set the icon is set according to the variant\"\n        },\n        {\n          \"name\": \"isExpandable\",\n          \"type\": \"boolean\",\n          \"description\": \"Flag indicating that the alert is expandable\",\n          \"defaultValue\": \"false\"\n        },\n        {\n          \"name\": \"isInline\",\n          \"type\": \"boolean\",\n          \"description\": \"Flag to indicate if the alert is inline\",\n          \"defaultValue\": \"false\"\n        },\n        {\n          \"name\": \"isLiveRegion\",\n          \"type\": \"boolean\",\n          \"description\": \"Flag to indicate if the alert is in a live region\",\n          \"defaultValue\": \"false\"\n        },\n        {\n          \"name\": \"isPlain\",\n          \"type\": \"boolean\",\n          \"description\": \"Flag to indicate if the alert is plain\",\n          \"defaultValue\": \"false\"\n        },\n        {\n          \"name\": \"onMouseEnter\",\n          \"type\": \"No type info\",\n          \"defaultValue\": \"() => {}\"\n        },\n        {\n          \"name\": \"onMouseLeave\",\n          \"type\": \"No type info\",\n          \"defaultValue\": \"() => {}\"\n        },\n        {\n          \"name\": \"onTimeout\",\n          \"type\": \"() => void\",\n          \"description\": \"Function to be executed on alert timeout. Relevant when the timeout prop is set\",\n          \"defaultValue\": \"() => {}\"\n        },\n        {\n          \"name\": \"ouiaSafe\",\n          \"type\": \"No type info\",\n          \"defaultValue\": \"true\"\n        },\n        {\n          \"name\": \"timeout\",\n          \"type\": \"number | boolean\",\n          \"description\": \"If set to true, the timeout is 8000 milliseconds. If a number is provided, alert will be dismissed after that amount of time in milliseconds.\",\n          \"defaultValue\": \"false\"\n        },\n        {\n          \"name\": \"timeoutAnimation\",\n          \"type\": \"number\",\n          \"description\": \"If the user hovers over the alert and `timeout` expires, this is how long to wait before finally dismissing the alert\",\n          \"defaultValue\": \"3000\"\n        },\n        {\n          \"name\": \"title\",\n          \"type\": \"React.ReactNode\",\n          \"description\": \"Title of the alert\",\n          \"required\": true\n        },\n        {\n          \"name\": \"titleHeadingLevel\",\n          \"type\": \"'h1' | 'h2' | 'h3' | 'h4' | 'h5' | 'h6'\",\n          \"description\": \"Sets the heading level to use for the alert title. Default is h4.\",\n          \"defaultValue\": \"'h4'\"\n        },\n        {\n          \"name\": \"toggleAriaLabel\",\n          \"type\": \"string\",\n          \"description\": \"Adds accessible text to the alert Toggle\",\n          \"defaultValue\": \"`${capitalize(variant)} alert details`\"\n        },\n        {\n          \"name\": \"tooltipPosition\",\n          \"type\": \"| TooltipPosition\\n| 'auto'\\n| 'top'\\n| 'bottom'\\n| 'left'\\n| 'right'\\n| 'top-start'\\n| 'top-end'\\n| 'bottom-start'\\n| 'bottom-end'\\n| 'left-start'\\n| 'left-end'\\n| 'right-start'\\n| 'right-end'\",\n          \"description\": \"Position of the tooltip which is displayed if text is truncated\"\n        },\n        {\n          \"name\": \"truncateTitle\",\n          \"type\": \"number\",\n          \"description\": \"Truncate title to number of lines\",\n          \"defaultValue\": \"0\"\n        },\n        {\n          \"name\": \"variant\",\n          \"type\": \"'success' | 'danger' | 'warning' | 'info' | 'default'\",\n          \"description\": \"Adds alert variant styles\",\n          \"defaultValue\": \"AlertVariant.default\"\n        },\n        {\n          \"name\": \"variantLabel\",\n          \"type\": \"string\",\n          \"description\": \"Variant label text for screen readers\",\n          \"defaultValue\": \"`${capitalize(variant)} alert:`\"\n        }\n      ]\n    },\n    {\n      \"name\": \"AlertActionCloseButton\",\n      \"description\": \"\",\n      \"props\": [\n        {\n          \"name\": \"aria-label\",\n          \"type\": \"string\",\n          \"description\": \"Aria Label for the Close button\",\n          \"defaultValue\": \"''\"\n        },\n        {\n          \"name\": \"className\",\n          \"type\": \"string\",\n          \"description\": \"Additional classes added to the AlertActionCloseButton\",\n          \"defaultValue\": \"''\"\n        },\n        {\n          \"name\": \"onClose\",\n          \"type\": \"() => void\",\n          \"description\": \"A callback for when the close button is clicked\",\n          \"defaultValue\": \"() => undefined as any\"\n        },\n        {\n          \"name\": \"variantLabel\",\n          \"type\": \"string\",\n          \"description\": \"Variant Label for the Close button\"\n        }\n      ]\n    },\n    {\n      \"name\": \"AlertActionLink\",\n      \"description\": \"\",\n      \"props\": [\n        {\n          \"name\": \"children\",\n          \"type\": \"string\",\n          \"description\": \"Content rendered inside the AlertLinkAction\"\n        },\n        {\n          \"name\": \"className\",\n          \"type\": \"string\",\n          \"description\": \"Additional classes added to the AlertActionLink\",\n          \"defaultValue\": \"''\"\n        }\n      ]\n    }\n  ],\n  \"cssPrefix\": [\n    \"pf-c-alert\"\n  ],\n  \"examples\": [\n    \"Types\",\n    \"Variations\",\n    \"Inline types\",\n    \"Inline variations\",\n    \"Inline plain types\",\n    \"Inline plain variations\",\n    \"Expandable\",\n    \"Static live region alert\",\n    \"Dynamic live region alert\",\n    \"Async live region alert\",\n    \"Alert timeout\",\n    \"Truncate\",\n    \"Custom icons\"\n  ]\n};\npageData.liveContext = {\n  UsersIcon,\n  BoxIcon,\n  DatabaseIcon,\n  ServerIcon,\n  LaptopIcon\n};\npageData.examples = {\n  'Types': props => \n    <Example {...pageData} {...props} {...{\"code\":\"import React from 'react';\\nimport { Alert } from '@patternfly/react-core';\\n\\nconst Types = () => (\\n  <React.Fragment>\\n    <Alert title=\\\"Default alert title\\\" />\\n    <Alert variant=\\\"info\\\" title=\\\"Info alert title\\\" />\\n    <Alert variant=\\\"success\\\" title=\\\"Success alert title\\\" />\\n    <Alert variant=\\\"warning\\\" title=\\\"Warning alert title\\\" />\\n    <Alert variant=\\\"danger\\\" title=\\\"Danger alert title\\\" />\\n  </React.Fragment>\\n)\",\"title\":\"Types\",\"lang\":\"ts\"}}>\n      \n    </Example>,\n  'Variations': props => \n    <Example {...pageData} {...props} {...{\"code\":\"import React from 'react';\\nimport { Alert, AlertActionCloseButton, AlertActionLink } from '@patternfly/react-core';\\n\\nconst Variations = () => (\\n  <React.Fragment>\\n    <Alert\\n      variant=\\\"success\\\"\\n      title=\\\"Success alert title\\\"\\n      actionClose={<AlertActionCloseButton onClose={() => alert('Clicked the close button')} />}\\n      actionLinks={\\n        <React.Fragment>\\n          <AlertActionLink onClick={() => alert('Clicked on View details')}>View details</AlertActionLink>\\n          <AlertActionLink onClick={() => alert('Clicked on Ignore')}>Ignore</AlertActionLink>\\n        </React.Fragment>\\n      }\\n    >\\n      <p>Success alert description. This should tell the user more information about the alert.</p>\\n    </Alert>\\n    <Alert variant=\\\"success\\\" title=\\\"Success alert title\\\" actionClose={<AlertActionCloseButton onClose={() => alert('Clicked the close button')} />}>\\n      <p>\\n        Success alert description. This should tell the user more information about the alert.{' '}\\n        <a href=\\\"#\\\">This is a link.</a>\\n      </p>\\n    </Alert>\\n    <Alert\\n      variant=\\\"success\\\"\\n      title=\\\"Success alert title\\\"\\n      actionClose={<AlertActionCloseButton onClose={() => alert('Clicked the close button')} />}\\n      actionLinks={\\n        <React.Fragment>\\n          <AlertActionLink onClick={() => alert('Clicked on View details')}>View details</AlertActionLink>\\n          <AlertActionLink onClick={() => alert('Clicked on Ignore')}>Ignore</AlertActionLink>\\n        </React.Fragment>\\n      }\\n    />\\n    <Alert variant=\\\"success\\\" title=\\\"Success alert title\\\" actionClose={<AlertActionCloseButton onClose={() => alert('Clicked the close button')} />} />\\n    <Alert variant=\\\"success\\\" title=\\\"h1 Success alert title\\\" titleHeadingLevel=\\\"h1\\\" />\\n    <Alert variant=\\\"success\\\" title=\\\"h6 Success alert title\\\" titleHeadingLevel=\\\"h6\\\" />\\n    </React.Fragment>\\n)\",\"title\":\"Variations\",\"lang\":\"ts\"}}>\n      \n    </Example>,\n  'Inline types': props => \n    <Example {...pageData} {...props} {...{\"code\":\"import React from 'react';\\nimport { Alert } from '@patternfly/react-core';\\n\\nconst InlineTypes = () => (\\n  <React.Fragment>\\n    <Alert variant=\\\"default\\\" isInline title=\\\"Default inline alert title\\\" />\\n    <Alert variant=\\\"info\\\" isInline title=\\\"Info inline alert title\\\" />\\n    <Alert variant=\\\"success\\\" isInline title=\\\"Success inline alert title\\\" />\\n    <Alert variant=\\\"warning\\\" isInline title=\\\"Warning inline alert title\\\" />\\n    <Alert variant=\\\"danger\\\" isInline title=\\\"Danger inline alert title\\\" />\\n  </React.Fragment>\\n)\",\"title\":\"Inline types\",\"lang\":\"ts\"}}>\n      \n    </Example>,\n  'Inline variations': props => \n    <Example {...pageData} {...props} {...{\"code\":\"import React from 'react';\\nimport { Alert, AlertActionCloseButton, AlertActionLink } from '@patternfly/react-core';\\n\\nconst InlineVariations = () => (\\n  <React.Fragment>\\n    <Alert\\n      isInline\\n      variant=\\\"success\\\"\\n      title=\\\"Success alert title\\\"\\n      actionClose={<AlertActionCloseButton onClose={() => alert('Clicked the close button')} />}\\n      actionLinks={\\n        <React.Fragment>\\n          <AlertActionLink onClick={() => alert('Clicked on View details')}>View details</AlertActionLink>\\n          <AlertActionLink onClick={() => alert('Clicked on Ignore')}>Ignore</AlertActionLink>\\n        </React.Fragment>\\n      }\\n    >\\n      <p>Success alert description. This should tell the user more information about the alert.</p>\\n    </Alert>\\n    <Alert isInline variant=\\\"success\\\" title=\\\"Success alert title\\\" actionClose={<AlertActionCloseButton onClose={() => alert('Clicked the close button')} />}>\\n      <p>\\n        Success alert description. This should tell the user more information about the alert.{' '}\\n        <a href=\\\"#\\\">This is a link.</a>\\n      </p>\\n    </Alert>\\n    <Alert\\n      isInline\\n      variant=\\\"success\\\"\\n      title=\\\"Success alert title\\\"\\n      actionClose={<AlertActionCloseButton onClose={() => alert('Clicked the close button')} />}\\n      actionLinks={\\n        <React.Fragment>\\n          <AlertActionLink onClick={() => alert('Clicked on View details')}>View details</AlertActionLink>\\n          <AlertActionLink onClick={() => alert('Clicked on Ignore')}>Ignore</AlertActionLink>\\n        </React.Fragment>\\n      }\\n    />\\n    <Alert\\n      isInline\\n      variant=\\\"success\\\"\\n      title=\\\"Success alert title\\\"\\n      actionClose={<AlertActionCloseButton onClose={() => alert('Clicked the close button')} />}\\n    />\\n    <Alert isInline variant=\\\"success\\\" title=\\\"Success alert title\\\" />\\n  </React.Fragment>\\n)\",\"title\":\"Inline variations\",\"lang\":\"ts\"}}>\n      \n    </Example>,\n  'Inline plain types': props => \n    <Example {...pageData} {...props} {...{\"code\":\"import React from 'react';\\nimport { Alert } from '@patternfly/react-core';\\n\\nconst InlinePlainTypes = () => (\\n  <React.Fragment>\\n    <Alert variant=\\\"default\\\" isInline isPlain title=\\\"Default inline alert title\\\" />\\n    <Alert variant=\\\"info\\\" isInline isPlain title=\\\"Info inline alert title\\\" />\\n    <Alert variant=\\\"success\\\" isInline isPlain title=\\\"Success inline alert title\\\" />\\n    <Alert variant=\\\"warning\\\" isInline isPlain title=\\\"Warning inline alert title\\\" />\\n    <Alert variant=\\\"danger\\\" isInline isPlain title=\\\"Danger inline alert title\\\" />\\n  </React.Fragment>\\n)\",\"title\":\"Inline plain types\",\"lang\":\"ts\"}}>\n      \n    </Example>,\n  'Inline plain variations': props => \n    <Example {...pageData} {...props} {...{\"code\":\"import React from 'react';\\nimport { Alert, AlertActionCloseButton, AlertActionLink } from '@patternfly/react-core';\\n\\nconst InlinePlainVariations = () => (\\n  <Alert\\n    isInline\\n    isPlain\\n    variant=\\\"success\\\"\\n    title=\\\"Success alert title\\\"\\n  >\\n    <p>Success alert description. This should tell the user more information about the alert.</p>\\n  </Alert>\\n)\",\"title\":\"Inline plain variations\",\"lang\":\"ts\"}}>\n      \n      <p {...{\"className\":\"ws-p\"}}>\n        {`It is not recommended to use an inline plain alert with actionClose nor actionLinks.`}\n      </p>\n    </Example>,\n  'Expandable': props => \n    <Example {...pageData} {...props} {...{\"code\":\"import React from 'react';\\nimport { Alert, AlertActionCloseButton, AlertActionLink } from '@patternfly/react-core';\\n\\nconst Expandable = () => (\\n  <React.Fragment>\\n    <Alert\\n      isExpandable\\n      variant=\\\"success\\\"\\n      title=\\\"Success alert title\\\"\\n      actionClose={<AlertActionCloseButton onClose={() => alert('Clicked the close button')} />}\\n      actionLinks={\\n        <React.Fragment>\\n          <AlertActionLink onClick={() => alert('Clicked on View details')}>View details</AlertActionLink>\\n          <AlertActionLink onClick={() => alert('Clicked on Ignore')}>Ignore</AlertActionLink>\\n        </React.Fragment>\\n      }\\n    >\\n      <p>Success alert description. This should tell the user more information about the alert.</p>\\n    </Alert>\\n    <Alert\\n      isExpandable\\n      isInline\\n      variant=\\\"success\\\"\\n      title=\\\"Success alert title\\\"\\n      actionClose={<AlertActionCloseButton onClose={() => alert('Clicked the close button')} />}\\n      actionLinks={\\n        <React.Fragment>\\n          <AlertActionLink onClick={() => alert('Clicked on View details')}>View details</AlertActionLink>\\n          <AlertActionLink onClick={() => alert('Clicked on Ignore')}>Ignore</AlertActionLink>\\n        </React.Fragment>\\n      } \\n    >\\n      <p>Success alert description. This should tell the user more information about the alert.</p>\\n    </Alert>\\n  </React.Fragment>\\n)\",\"title\":\"Expandable\",\"lang\":\"ts\"}}>\n      \n      <p {...{\"className\":\"ws-p\"}}>\n        {`It is not recommended to use an expandable alert within a toast Alert group. In such a case, the Alert could timeout before users would have time to interact and view the entire Alert.`}\n      </p>\n    </Example>,\n  'Static live region alert': props => \n    <Example {...pageData} {...props} {...{\"code\":\"import React from 'react';\\nimport { Alert, AlertActionCloseButton } from '@patternfly/react-core';\\n\\nconst StaticLiveRegionAlert = () => (\\n  <React.Fragment>\\n    <Alert\\n      isLiveRegion\\n      variant=\\\"info\\\"\\n      title=\\\"Default live region configuration\\\"\\n      actionClose={<AlertActionCloseButton onClose={() => alert('Clicked the close button')} />}\\n    >\\n      This alert uses the recommended <code>isLiveRegion</code> prop to automatically set ARIA attributes and CSS classes.\\n    </Alert>\\n    <Alert\\n      aria-live=\\\"assertive\\\"\\n      aria-relevant=\\\"additions text\\\"\\n      aria-atomic=\\\"true\\\"\\n      variant=\\\"info\\\"\\n      title=\\\"Customized live region\\\"\\n      actionClose={<AlertActionCloseButton onClose={() => alert('Clicked the close button')} />}\\n    >\\n      You can alternatively omit the <code>isLiveRegion</code> prop to specify ARIA attributes and CSS manually on\\n      the containing element.\\n    </Alert>\\n  </React.Fragment>\\n)\",\"title\":\"Static live region alert\",\"lang\":\"ts\"}}>\n      \n    </Example>,\n  'Dynamic live region alert': props => \n    <Example {...pageData} {...props} {...{\"code\":\"import React from 'react';\\nimport { Alert, AlertGroup, AlertVariant, InputGroup } from '@patternfly/react-core';\\n\\ninterface AlertInfo {\\n  title: string;\\n  variant: AlertVariant;\\n  key: number;\\n}\\n\\nexport const DynamicLiveRegionAlert: React.FunctionComponent = () => {\\n  const [alerts, setAlerts] = React.useState<AlertInfo[]>([]);\\n  const getUniqueId: () => number = () => new Date().getTime();\\n  const btnClasses = ['pf-c-button', 'pf-m-secondary'].join(' ');\\n\\n  const addAlert = (alertInfo: AlertInfo) => {\\n    setAlerts(prevAlertInfo => [...prevAlertInfo, alertInfo]);\\n  };\\n\\n  const addSuccessAlert = () => {\\n    addAlert({\\n      title: 'Single success alert',\\n      variant: AlertVariant.success,\\n      key: getUniqueId()\\n    });\\n  };\\n  const addInfoAlert = () => {\\n    addAlert({\\n      title: 'Single info alert',\\n      variant: AlertVariant.info,\\n      key: getUniqueId()\\n    });\\n  };\\n  const addDangerAlert = () => {\\n    addAlert({\\n      title: 'Single danger alert',\\n      variant: AlertVariant.danger,\\n      key: getUniqueId()\\n    });\\n  };\\n\\n  return (\\n    <React.Fragment>\\n      <InputGroup style={{ marginBottom: '16px' }}>\\n        <button onClick={addSuccessAlert} type=\\\"button\\\" className={btnClasses}>\\n          Add single success alert\\n        </button>\\n        <button onClick={addInfoAlert} type=\\\"button\\\" className={btnClasses}>\\n          Add single info alert\\n        </button>\\n        <button onClick={addDangerAlert} type=\\\"button\\\" className={btnClasses}>\\n          Add single danger alert\\n        </button>\\n      </InputGroup>\\n      <AlertGroup isLiveRegion aria-live=\\\"polite\\\" aria-relevant=\\\"additions text\\\" aria-atomic=\\\"false\\\">\\n        {alerts.map(({ title, variant, key }) => (\\n          <Alert variant={variant} title={title} key={key} />\\n        ))}\\n      </AlertGroup>\\n    </React.Fragment>\\n  );\\n};\\n\",\"title\":\"Dynamic live region alert\",\"lang\":\"ts\"}}>\n      \n      <p {...{\"className\":\"ws-p\"}}>\n        {`Alerts asynchronously appended into dynamic AlertGroups with isLiveRegion will be announced to assistive technology at the moment the change happens, following the strategy used for aria-atomic, which defaults to false. This means only changes of type \"addition\" will be announced.`}\n      </p>\n    </Example>,\n  'Async live region alert': props => \n    <Example {...pageData} {...props} {...{\"code\":\"import React from 'react';\\nimport { Alert, AlertGroup, AlertVariant, ToggleGroup, ToggleGroupItem } from '@patternfly/react-core';\\n\\ninterface AlertInfo {\\n  title: string;\\n  variant: AlertVariant;\\n  key: number;\\n}\\n\\nexport const AsyncLiveRegionAlert: React.FunctionComponent = () => {\\n  const [alerts, setAlerts] = React.useState<AlertInfo[]>([]);\\n  const [isActive, setIsActive] = React.useState(false);\\n  const getUniqueId: () => number = () => new Date().getTime();\\n\\n  const addAlert = (alertInfo: AlertInfo) => {\\n    setAlerts(prevAlertInfo => [...prevAlertInfo, alertInfo]);\\n  };\\n\\n  React.useEffect(() => {\\n    let timer = null;\\n    if (isActive) {\\n      timer = setInterval(() => {\\n        addAlert({\\n          title: `Async alert number ${alerts.length + 1}`,\\n          variant: AlertVariant.info,\\n          key: getUniqueId()\\n        });\\n      }, 4500);\\n    } else {\\n      clearInterval(timer);\\n    }\\n\\n    return () => {\\n      clearInterval(timer);\\n    };\\n  }, [isActive, alerts]);\\n\\n  return (\\n    <React.Fragment>\\n      <ToggleGroup aria-label=\\\"Toggle asynchronous alerts\\\">\\n        <ToggleGroupItem\\n          text=\\\"Async alerts on\\\"\\n          buttonId=\\\"async-alerts-on\\\"\\n          isSelected={isActive}\\n          onChange={() => setIsActive(true)}\\n        />\\n        <ToggleGroupItem\\n          text=\\\"Async alerts off\\\"\\n          buttonId=\\\"async-alerts-off\\\"\\n          isSelected={!isActive}\\n          onChange={() => setIsActive(false)}\\n        />\\n      </ToggleGroup>\\n      <AlertGroup isLiveRegion>\\n        {alerts.map(({ title, variant, key }) => (\\n          <Alert variant={variant} title={title} key={key} />\\n        ))}\\n      </AlertGroup>\\n    </React.Fragment>\\n  );\\n};\\n\",\"title\":\"Async live region alert\",\"lang\":\"ts\"}}>\n      \n      <p {...{\"className\":\"ws-p\"}}>\n        {`This shows how an alert could be triggered by an asynchronous event in the application. Note that you can customize how the alert will be announced to assistive technology. See the alert accessibility tab for more information.`}\n      </p>\n    </Example>,\n  'Alert timeout': props => \n    <Example {...pageData} {...props} {...{\"code\":\"import React from 'react';\\nimport { Alert, AlertActionLink, AlertGroup, Button } from '@patternfly/react-core';\\n\\nconst AlertTimeout: React.FunctionComponent = () => {\\n  const [alerts, setAlerts] = React.useState<React.ReactNode[]>([]);\\n  const onClick = () => {\\n    const timeout = 8000;\\n    setAlerts(prevAlerts => {\\n      return [...prevAlerts,\\n        <Alert title=\\\"Default timeout Alert\\\" timeout={timeout} actionLinks={\\n          <React.Fragment>\\n            <AlertActionLink>View details</AlertActionLink>\\n            <AlertActionLink>Ignore</AlertActionLink>\\n          </React.Fragment>\\n        }>\\n          This alert will dismiss after {`${timeout / 1000} seconds`}\\n        </Alert>\\n      ]\\n    });\\n  }\\n\\n  return (\\n    <React.Fragment>\\n      <Button variant=\\\"secondary\\\" onClick={onClick}>Add alert</Button>\\n      <Button variant=\\\"secondary\\\" onClick={() => setAlerts([])}>Remove all alerts</Button>\\n      <AlertGroup isLiveRegion>\\n        {alerts}\\n      </AlertGroup>\\n    </React.Fragment>\\n  );\\n};\",\"title\":\"Alert timeout\",\"lang\":\"ts\"}}>\n      \n    </Example>,\n  'Truncate': props => \n    <Example {...pageData} {...props} {...{\"code\":\"import React from 'react';\\nimport { Alert } from '@patternfly/react-core';\\n\\nconst Truncate = () => (\\n  <React.Fragment>\\n    <Alert variant=\\\"info\\\" truncateTitle={1} title={`\\n    Lorem ipsum dolor sit amet, consectetur adipiscing elit. Curabitur pellentesque neque cursus enim fringilla tincidunt. Proin lobortis aliquam dictum. Nam vel ullamcorper nulla, nec blandit dolor. Vivamus pellentesque neque justo, nec accumsan nulla rhoncus id. Suspendisse mollis, tortor quis faucibus volutpat, sem leo fringilla turpis, ac lacinia augue metus in nulla. Cras vestibulum lacinia orci. Pellentesque sodales consequat interdum. Sed porttitor tincidunt metus nec iaculis. Pellentesque non commodo justo. Morbi feugiat rhoncus neque, vitae facilisis diam aliquam nec. Sed dapibus vitae quam at tristique. Nunc vel commodo mi. Mauris et rhoncus leo.\\n    `} />\\n    <Alert variant=\\\"warning\\\" truncateTitle={2} title={`\\n    Lorem ipsum dolor sit amet, consectetur adipiscing elit. Curabitur pellentesque neque cursus enim fringilla tincidunt. Proin lobortis aliquam dictum. Nam vel ullamcorper nulla, nec blandit dolor. Vivamus pellentesque neque justo, nec accumsan nulla rhoncus id. Suspendisse mollis, tortor quis faucibus volutpat, sem leo fringilla turpis, ac lacinia augue metus in nulla. Cras vestibulum lacinia orci. Pellentesque sodales consequat interdum. Sed porttitor tincidunt metus nec iaculis. Pellentesque non commodo justo. Morbi feugiat rhoncus neque, vitae facilisis diam aliquam nec. Sed dapibus vitae quam at tristique. Nunc vel commodo mi. Mauris et rhoncus leo.\\n    `} />\\n    <Alert variant=\\\"danger\\\" truncateTitle={3} title={`\\n    Lorem ipsum dolor sit amet, consectetur adipiscing elit. Curabitur pellentesque neque cursus enim fringilla tincidunt. Proin lobortis aliquam dictum. Nam vel ullamcorper nulla, nec blandit dolor. Vivamus pellentesque neque justo, nec accumsan nulla rhoncus id. Suspendisse mollis, tortor quis faucibus volutpat, sem leo fringilla turpis, ac lacinia augue metus in nulla. Cras vestibulum lacinia orci. Pellentesque sodales consequat interdum. Sed porttitor tincidunt metus nec iaculis. Pellentesque non commodo justo. Morbi feugiat rhoncus neque, vitae facilisis diam aliquam nec. Sed dapibus vitae quam at tristique. Nunc vel commodo mi. Mauris et rhoncus leo.\\n    `} />\\n  </React.Fragment>\\n)\",\"title\":\"Truncate\",\"lang\":\"ts\"}}>\n      \n    </Example>,\n  'Custom icons': props => \n    <Example {...pageData} {...props} {...{\"code\":\"import React from 'react';\\nimport { Alert } from '@patternfly/react-core';\\nimport UsersIcon from '@patternfly/react-icons/dist/esm/icons/users-icon';\\nimport BoxIcon from '@patternfly/react-icons/dist/esm/icons/box-icon';\\nimport DatabaseIcon from '@patternfly/react-icons/dist/esm/icons/database-icon';\\nimport ServerIcon from '@patternfly/react-icons/dist/esm/icons/server-icon';\\nimport LaptopIcon from '@patternfly/react-icons/dist/esm/icons/laptop-icon';\\n\\nconst CustomIcons = () => (\\n  <React.Fragment>\\n    <Alert customIcon={<UsersIcon />} title=\\\"Default alert title\\\" />\\n    <Alert customIcon={<BoxIcon />} variant=\\\"info\\\" title=\\\"Info alert title\\\" />\\n    <Alert customIcon={<DatabaseIcon />} variant=\\\"success\\\" title=\\\"Success alert title\\\" />\\n    <Alert customIcon={<ServerIcon />} variant=\\\"warning\\\" title=\\\"Warning alert title\\\" />\\n    <Alert customIcon={<LaptopIcon />} variant=\\\"danger\\\" title=\\\"Danger alert title\\\" />\\n  </React.Fragment>\\n)\",\"title\":\"Custom icons\",\"lang\":\"ts\"}}>\n      \n    </Example>\n};\n\nconst Component = () => (\n  <React.Fragment>\n    <AutoLinkHeader {...{\"id\":\"examples\",\"size\":\"h2\",\"className\":\"ws-title ws-h2\"}}>\n      {`Examples`}\n    </AutoLinkHeader>\n    {React.createElement(pageData.examples[\"Types\"])}\n    {React.createElement(pageData.examples[\"Variations\"])}\n    {React.createElement(pageData.examples[\"Inline types\"])}\n    {React.createElement(pageData.examples[\"Inline variations\"])}\n    {React.createElement(pageData.examples[\"Inline plain types\"])}\n    {React.createElement(pageData.examples[\"Inline plain variations\"])}\n    {React.createElement(pageData.examples[\"Expandable\"])}\n    {React.createElement(pageData.examples[\"Static live region alert\"])}\n    {React.createElement(pageData.examples[\"Dynamic live region alert\"])}\n    {React.createElement(pageData.examples[\"Async live region alert\"])}\n    {React.createElement(pageData.examples[\"Alert timeout\"])}\n    {React.createElement(pageData.examples[\"Truncate\"])}\n    {React.createElement(pageData.examples[\"Custom icons\"])}\n  </React.Fragment>\n);\nComponent.displayName = 'ComponentsAlertReactDocs';\nComponent.pageData = pageData;\n\nexport default Component;\n"],"mappings":";;AAAA,OAAOA,KAAP,MAAkB,OAAlB;AACA,SAASC,cAAT,EAAyBC,OAAzB,EAAkCC,IAAI,IAAIC,mBAA1C,QAAqE,iCAArE;AACA,OAAO,2FAAP;AACA,OAAOC,SAAP,MAAsB,mDAAtB;AACA,OAAOC,OAAP,MAAoB,iDAApB;AACA,OAAOC,YAAP,MAAyB,sDAAzB;AACA,OAAOC,UAAP,MAAuB,oDAAvB;AACA,OAAOC,UAAP,MAAuB,oDAAvB;AACA,IAAMC,QAAQ,GAAG;EACf,MAAM,OADS;EAEf,WAAW,YAFI;EAGf,UAAU,OAHK;EAIf,QAAQ,yBAJO;EAKf,cAAc,mIALC;EAMf,kBAAkB,CAChB;IACE,QAAQ,OADV;IAEE,eAAe,EAFjB;IAGE,SAAS,CACP;MACE,QAAQ,aADV;MAEE,QAAQ,iBAFV;MAGE,eAAe;IAHjB,CADO,EAMP;MACE,QAAQ,aADV;MAEE,QAAQ,iBAFV;MAGE,eAAe;IAHjB,CANO,EAWP;MACE,QAAQ,YADV;MAEE,QAAQ,QAFV;MAGE,eAAe,mCAHjB;MAIE,gBAAgB;IAJlB,CAXO,EAiBP;MACE,QAAQ,UADV;MAEE,QAAQ,iBAFV;MAGE,eAAe,mCAHjB;MAIE,gBAAgB;IAJlB,CAjBO,EAuBP;MACE,QAAQ,WADV;MAEE,QAAQ,QAFV;MAGE,eAAe,uCAHjB;MAIE,gBAAgB;IAJlB,CAvBO,EA6BP;MACE,QAAQ,YADV;MAEE,QAAQ,iBAFV;MAGE,eAAe;IAHjB,CA7BO,EAkCP;MACE,QAAQ,cADV;MAEE,QAAQ,SAFV;MAGE,eAAe,8CAHjB;MAIE,gBAAgB;IAJlB,CAlCO,EAwCP;MACE,QAAQ,UADV;MAEE,QAAQ,SAFV;MAGE,eAAe,yCAHjB;MAIE,gBAAgB;IAJlB,CAxCO,EA8CP;MACE,QAAQ,cADV;MAEE,QAAQ,SAFV;MAGE,eAAe,mDAHjB;MAIE,gBAAgB;IAJlB,CA9CO,EAoDP;MACE,QAAQ,SADV;MAEE,QAAQ,SAFV;MAGE,eAAe,wCAHjB;MAIE,gBAAgB;IAJlB,CApDO,EA0DP;MACE,QAAQ,cADV;MAEE,QAAQ,cAFV;MAGE,gBAAgB;IAHlB,CA1DO,EA+DP;MACE,QAAQ,cADV;MAEE,QAAQ,cAFV;MAGE,gBAAgB;IAHlB,CA/DO,EAoEP;MACE,QAAQ,WADV;MAEE,QAAQ,YAFV;MAGE,eAAe,iFAHjB;MAIE,gBAAgB;IAJlB,CApEO,EA0EP;MACE,QAAQ,UADV;MAEE,QAAQ,cAFV;MAGE,gBAAgB;IAHlB,CA1EO,EA+EP;MACE,QAAQ,SADV;MAEE,QAAQ,kBAFV;MAGE,eAAe,+IAHjB;MAIE,gBAAgB;IAJlB,CA/EO,EAqFP;MACE,QAAQ,kBADV;MAEE,QAAQ,QAFV;MAGE,eAAe,uHAHjB;MAIE,gBAAgB;IAJlB,CArFO,EA2FP;MACE,QAAQ,OADV;MAEE,QAAQ,iBAFV;MAGE,eAAe,oBAHjB;MAIE,YAAY;IAJd,CA3FO,EAiGP;MACE,QAAQ,mBADV;MAEE,QAAQ,yCAFV;MAGE,eAAe,mEAHjB;MAIE,gBAAgB;IAJlB,CAjGO,EAuGP;MACE,QAAQ,iBADV;MAEE,QAAQ,QAFV;MAGE,eAAe,0CAHjB;MAIE,gBAAgB;IAJlB,CAvGO,EA6GP;MACE,QAAQ,iBADV;MAEE,QAAQ,mMAFV;MAGE,eAAe;IAHjB,CA7GO,EAkHP;MACE,QAAQ,eADV;MAEE,QAAQ,QAFV;MAGE,eAAe,mCAHjB;MAIE,gBAAgB;IAJlB,CAlHO,EAwHP;MACE,QAAQ,SADV;MAEE,QAAQ,uDAFV;MAGE,eAAe,2BAHjB;MAIE,gBAAgB;IAJlB,CAxHO,EA8HP;MACE,QAAQ,cADV;MAEE,QAAQ,QAFV;MAGE,eAAe,uCAHjB;MAIE,gBAAgB;IAJlB,CA9HO;EAHX,CADgB,EA0IhB;IACE,QAAQ,wBADV;IAEE,eAAe,EAFjB;IAGE,SAAS,CACP;MACE,QAAQ,YADV;MAEE,QAAQ,QAFV;MAGE,eAAe,iCAHjB;MAIE,gBAAgB;IAJlB,CADO,EAOP;MACE,QAAQ,WADV;MAEE,QAAQ,QAFV;MAGE,eAAe,wDAHjB;MAIE,gBAAgB;IAJlB,CAPO,EAaP;MACE,QAAQ,SADV;MAEE,QAAQ,YAFV;MAGE,eAAe,iDAHjB;MAIE,gBAAgB;IAJlB,CAbO,EAmBP;MACE,QAAQ,cADV;MAEE,QAAQ,QAFV;MAGE,eAAe;IAHjB,CAnBO;EAHX,CA1IgB,EAuKhB;IACE,QAAQ,iBADV;IAEE,eAAe,EAFjB;IAGE,SAAS,CACP;MACE,QAAQ,UADV;MAEE,QAAQ,QAFV;MAGE,eAAe;IAHjB,CADO,EAMP;MACE,QAAQ,WADV;MAEE,QAAQ,QAFV;MAGE,eAAe,iDAHjB;MAIE,gBAAgB;IAJlB,CANO;EAHX,CAvKgB,CANH;EA+Lf,aAAa,CACX,YADW,CA/LE;EAkMf,YAAY,CACV,OADU,EAEV,YAFU,EAGV,cAHU,EAIV,mBAJU,EAKV,oBALU,EAMV,yBANU,EAOV,YAPU,EAQV,0BARU,EASV,2BATU,EAUV,yBAVU,EAWV,eAXU,EAYV,UAZU,EAaV,cAbU;AAlMG,CAAjB;AAkNAA,QAAQ,CAACC,WAAT,GAAuB;EACrBN,SAAS,EAATA,SADqB;EAErBC,OAAO,EAAPA,OAFqB;EAGrBC,YAAY,EAAZA,YAHqB;EAIrBC,UAAU,EAAVA,UAJqB;EAKrBC,UAAU,EAAVA;AALqB,CAAvB;AAOAC,QAAQ,CAACE,QAAT,GAAoB;EAClB,SAAS,eAAAC,KAAK;IAAA,oBACZ,oBAAC,OAAD,eAAaH,QAAb,EAA2BG,KAA3B;MAAuC,QAAO,2bAA9C;MAA0e,SAAQ,OAAlf;MAA0f,QAAO;IAAjgB,GADY;EAAA,CADI;EAKlB,cAAc,oBAAAA,KAAK;IAAA,oBACjB,oBAAC,OAAD,eAAaH,QAAb,EAA2BG,KAA3B;MAAuC,QAAO,m4DAA9C;MAAk7D,SAAQ,YAA17D;MAAu8D,QAAO;IAA98D,GADiB;EAAA,CALD;EASlB,gBAAgB,qBAAAA,KAAK;IAAA,oBACnB,oBAAC,OAAD,eAAaH,QAAb,EAA2BG,KAA3B;MAAuC,QAAO,qiBAA9C;MAAolB,SAAQ,cAA5lB;MAA2mB,QAAO;IAAlnB,GADmB;EAAA,CATH;EAalB,qBAAqB,0BAAAA,KAAK;IAAA,oBACxB,oBAAC,OAAD,eAAaH,QAAb,EAA2BG,KAA3B;MAAuC,QAAO,02DAA9C;MAAy5D,SAAQ,mBAAj6D;MAAq7D,QAAO;IAA57D,GADwB;EAAA,CAbR;EAiBlB,sBAAsB,0BAAAA,KAAK;IAAA,oBACzB,oBAAC,OAAD,eAAaH,QAAb,EAA2BG,KAA3B;MAAuC,QAAO,klBAA9C;MAAioB,SAAQ,oBAAzoB;MAA8pB,QAAO;IAArqB,GADyB;EAAA,CAjBT;EAqBlB,2BAA2B,+BAAAA,KAAK;IAAA,oBAC9B,oBAAC,OAAD,eAAaH,QAAb,EAA2BG,KAA3B;MAAuC,QAAO,uXAA9C;MAAsa,SAAQ,yBAA9a;MAAwc,QAAO;IAA/c,iBAEE;MAAQ,aAAY;IAApB,0FAFF,CAD8B;EAAA,CArBd;EA4BlB,cAAc,oBAAAA,KAAK;IAAA,oBACjB,oBAAC,OAAD,eAAaH,QAAb,EAA2BG,KAA3B;MAAuC,QAAO,u4CAA9C;MAAs7C,SAAQ,YAA97C;MAA28C,QAAO;IAAl9C,iBAEE;MAAQ,aAAY;IAApB,8LAFF,CADiB;EAAA,CA5BD;EAmClB,4BAA4B,+BAAAA,KAAK;IAAA,oBAC/B,oBAAC,OAAD,eAAaH,QAAb,EAA2BG,KAA3B;MAAuC,QAAO,i9BAA9C;MAAggC,SAAQ,0BAAxgC;MAAmiC,QAAO;IAA1iC,GAD+B;EAAA,CAnCf;EAuClB,6BAA6B,gCAAAA,KAAK;IAAA,oBAChC,oBAAC,OAAD,eAAaH,QAAb,EAA2BG,KAA3B;MAAuC,QAAO,w2DAA9C;MAAu5D,SAAQ,2BAA/5D;MAA27D,QAAO;IAAl8D,iBAEE;MAAQ,aAAY;IAApB,iSAFF,CADgC;EAAA,CAvChB;EA8ClB,2BAA2B,8BAAAA,KAAK;IAAA,oBAC9B,oBAAC,OAAD,eAAaH,QAAb,EAA2BG,KAA3B;MAAuC,QAAO,wtDAA9C;MAAuwD,SAAQ,yBAA/wD;MAAyyD,QAAO;IAAhzD,iBAEE;MAAQ,aAAY;IAApB,wOAFF,CAD8B;EAAA,CA9Cd;EAqDlB,iBAAiB,sBAAAA,KAAK;IAAA,oBACpB,oBAAC,OAAD,eAAaH,QAAb,EAA2BG,KAA3B;MAAuC,QAAO,khCAA9C;MAAikC,SAAQ,eAAzkC;MAAylC,QAAO;IAAhmC,GADoB;EAAA,CArDJ;EAyDlB,YAAY,kBAAAA,KAAK;IAAA,oBACf,oBAAC,OAAD,eAAaH,QAAb,EAA2BG,KAA3B;MAAuC,QAAO,izEAA9C;MAAg2E,SAAQ,UAAx2E;MAAm3E,QAAO;IAA13E,GADe;EAAA,CAzDC;EA6DlB,gBAAgB,qBAAAA,KAAK;IAAA,oBACnB,oBAAC,OAAD,eAAaH,QAAb,EAA2BG,KAA3B;MAAuC,QAAO,68BAA9C;MAA4/B,SAAQ,cAApgC;MAAmhC,QAAO;IAA1hC,GADmB;EAAA;AA7DH,CAApB;;AAmEA,IAAMC,SAAS,GAAG,SAAZA,SAAY;EAAA,oBAChB,oBAAC,KAAD,CAAO,QAAP,qBACE,oBAAC,cAAD;IAAqB,MAAK,UAA1B;IAAqC,QAAO,IAA5C;IAAiD,aAAY;EAA7D,cADF,EAIGd,KAAK,CAACe,aAAN,CAAoBL,QAAQ,CAACE,QAAT,CAAkB,OAAlB,CAApB,CAJH,EAKGZ,KAAK,CAACe,aAAN,CAAoBL,QAAQ,CAACE,QAAT,CAAkB,YAAlB,CAApB,CALH,EAMGZ,KAAK,CAACe,aAAN,CAAoBL,QAAQ,CAACE,QAAT,CAAkB,cAAlB,CAApB,CANH,EAOGZ,KAAK,CAACe,aAAN,CAAoBL,QAAQ,CAACE,QAAT,CAAkB,mBAAlB,CAApB,CAPH,EAQGZ,KAAK,CAACe,aAAN,CAAoBL,QAAQ,CAACE,QAAT,CAAkB,oBAAlB,CAApB,CARH,EASGZ,KAAK,CAACe,aAAN,CAAoBL,QAAQ,CAACE,QAAT,CAAkB,yBAAlB,CAApB,CATH,EAUGZ,KAAK,CAACe,aAAN,CAAoBL,QAAQ,CAACE,QAAT,CAAkB,YAAlB,CAApB,CAVH,EAWGZ,KAAK,CAACe,aAAN,CAAoBL,QAAQ,CAACE,QAAT,CAAkB,0BAAlB,CAApB,CAXH,EAYGZ,KAAK,CAACe,aAAN,CAAoBL,QAAQ,CAACE,QAAT,CAAkB,2BAAlB,CAApB,CAZH,EAaGZ,KAAK,CAACe,aAAN,CAAoBL,QAAQ,CAACE,QAAT,CAAkB,yBAAlB,CAApB,CAbH,EAcGZ,KAAK,CAACe,aAAN,CAAoBL,QAAQ,CAACE,QAAT,CAAkB,eAAlB,CAApB,CAdH,EAeGZ,KAAK,CAACe,aAAN,CAAoBL,QAAQ,CAACE,QAAT,CAAkB,UAAlB,CAApB,CAfH,EAgBGZ,KAAK,CAACe,aAAN,CAAoBL,QAAQ,CAACE,QAAT,CAAkB,cAAlB,CAApB,CAhBH,CADgB;AAAA,CAAlB;;AAoBAE,SAAS,CAACE,WAAV,GAAwB,0BAAxB;AACAF,SAAS,CAACJ,QAAV,GAAqBA,QAArB;AAEA,eAAeI,SAAf"},"metadata":{},"sourceType":"module"}